clickuptosql/__init__.py
clickuptosql-1.1.0.dist-info/LICENSE
clickuptosql-1.1.0.dist-info/METADATA
clickuptosql-1.1.0.dist-info/WHEEL
clickuptosql-1.1.0.dist-info/top_level.txt
clickuptosql-1.1.0.dist-info/RECORD
