Metadata-Version: 2.1
Name: clickuptosql
Version: 1.1.0
Summary: Replicate ClickUp Database to a SQL Table.
Home-page: https://github.com/themagicalmammal/clickuptosql
Author: Dipan Nanda
Author-email: d19cyber@gmail.com
License: MIT
Project-URL: Documentation, https://github.com/themagicalmammal/clickuptosql/blob/main/README.md
Project-URL: Bug tracker, https://github.com/themagicalmammal/clickuptosql/issues
Keywords: python,ClickUp,Excel,pandas
Classifier: Development Status :: 5 - Production/Stable
Classifier: Intended Audience :: System Administrators
Classifier: Intended Audience :: Developers
Classifier: License :: OSI Approved :: GNU General Public License v3 (GPLv3)
Classifier: License :: OSI Approved :: GNU General Public License v3 or later (GPLv3+)
Classifier: Programming Language :: Python
Classifier: Programming Language :: Python :: 3
Classifier: Operating System :: Unix
Classifier: Operating System :: MacOS :: MacOS X
Classifier: Operating System :: Microsoft :: Windows
Classifier: Topic :: Utilities
License-File: LICENSE
Requires-Dist: SQLAlchemy (~=1.4.46)
Requires-Dist: pandas (~=1.5.2)
Requires-Dist: requests (~=2.28.1)
Requires-Dist: urllib3 (~=1.26.13)
Requires-Dist: tqdm (~=4.64.1)
